odoo10_addon_hr_payroll_cancel-10.0.1.0.1-py2.7-nspkg.pth
odoo/addons/hr_payroll_cancel/README.rst
odoo/addons/hr_payroll_cancel/__init__.py
odoo/addons/hr_payroll_cancel/__manifest__.py
odoo/addons/hr_payroll_cancel/i18n/cs_CZ.po
odoo/addons/hr_payroll_cancel/i18n/fr.po
odoo/addons/hr_payroll_cancel/i18n/hr_payroll_cancel.pot
odoo/addons/hr_payroll_cancel/i18n/sl.po
odoo/addons/hr_payroll_cancel/models/__init__.py
odoo/addons/hr_payroll_cancel/models/hr_payroll.py
odoo/addons/hr_payroll_cancel/static/description/icon.png
odoo/addons/hr_payroll_cancel/views/hr_payslip_view.xml
odoo10_addon_hr_payroll_cancel-10.0.1.0.1.dist-info/DESCRIPTION.rst
odoo10_addon_hr_payroll_cancel-10.0.1.0.1.dist-info/METADATA
odoo10_addon_hr_payroll_cancel-10.0.1.0.1.dist-info/RECORD
odoo10_addon_hr_payroll_cancel-10.0.1.0.1.dist-info/WHEEL
odoo10_addon_hr_payroll_cancel-10.0.1.0.1.dist-info/metadata.json
odoo10_addon_hr_payroll_cancel-10.0.1.0.1.dist-info/namespace_packages.txt
odoo10_addon_hr_payroll_cancel-10.0.1.0.1.dist-info/top_level.txt
